cadquery_direct_mesh_plugin/__init__.py
cadquery_direct_mesh_plugin/plugin.py
cadquery_direct_mesh_plugin-0.1.0.dist-info/METADATA
cadquery_direct_mesh_plugin-0.1.0.dist-info/WHEEL
cadquery_direct_mesh_plugin-0.1.0.dist-info/licenses/LICENSE
cadquery_direct_mesh_plugin-0.1.0.dist-info/RECORD
