Metadata-Version: 2.4
Name: cadquery_direct_mesh_plugin
Version: 0.1.0
Summary: CadQuery plugin to go directly from a CadQuery assembly to a mesh without relying on external dependencies.
Project-URL: Repository, https://github.com/jmwright/cadquery-direct-mesh-plugin.git
Project-URL: Bug Tracker, https://github.com/jmwright/cadquery-direct-mesh-plugin/issues
Author: Jeremy Wright
Maintainer: Jeremy Wright
License:                                  Apache License
License-File: LICENSE
Keywords: CAD,cadquery,design,engineering,mesh,meshing
Classifier: Development Status :: 4 - Beta
Classifier: Programming Language :: Python
Requires-Python: >=3.10
Requires-Dist: cadquery
Provides-Extra: dev
Requires-Dist: black; extra == 'dev'
Requires-Dist: pytest; extra == 'dev'
